cover_letter_automation/__init__.py
cover_letter_automation/agents/__init__.py
cover_letter_automation/agents/client.py
cover_letter_automation/agents/company_researcher.py
cover_letter_automation/agents/critic.py
cover_letter_automation/agents/job_description_ingester.py
cover_letter_automation/agents/resume_retriever.py
cover_letter_automation/agents/writer.py
cover_letter_automation/cli.py
cover_letter_automation/py.typed
cover_letter_automation/session.py
cover_letter_automation/tools.py
cover_letter_automation-0.4.1.dist-info/METADATA
cover_letter_automation-0.4.1.dist-info/WHEEL
cover_letter_automation-0.4.1.dist-info/entry_points.txt
cover_letter_automation-0.4.1.dist-info/RECORD
