Metadata-Version: 2.1
Name: cover_letter_automation
Version: 0.4.1
Summary: A Python package for ingesting job descriptions & resumes, and crafting cover letters that use the latter to satisfy the former
Home-page: https://github.com/shippy/cover_letter_automation/
License: Proprietary
Author: Simon Podhajsky
Author-email: simon.podhajsky@gmail.com
Requires-Python: >=3.11.8,<3.13
Classifier: License :: Other/Proprietary License
Classifier: Programming Language :: Python :: 3
Classifier: Programming Language :: Python :: 3.12
Requires-Dist: poethepoet (>=0.24.4)
Requires-Dist: pyautogen[retrievechat,teachable,websurfer] (>=0.2.21,<0.3.0)
Requires-Dist: pydantic (>=2.6.1)
Requires-Dist: python-dotenv (>=1.0.1,<2.0.0)
Requires-Dist: typer[all] (>=0.12.3,<0.13.0)
Project-URL: Repository, https://github.com/shippy/cover_letter_automation/
